MANIFEST.in
README.txt
setup.py
dobject/__init__.py
dobject.egg-info/PKG-INFO
dobject.egg-info/SOURCES.txt
dobject.egg-info/dependency_links.txt
dobject.egg-info/top_level.txt