Metadata-Version: 1.1
Name: dobject
Version: 0.1.1
Summary: Dictionary to object tools
Home-page: https://github.com/cyriac/dobject
Author: cyriac
Author-email: me@cyriacthomas.com
License: MIT
Download-URL: https://github.com/cyriac/dobject/archive/v0.1.1.tar.gz
Keywords: dobject,dictionary,object
Platform: UNKNOWN
